luadata/__init__.py
luadata/io/__init__.py
luadata/io/read.py
luadata/io/write.py
luadata/serializer/__init__.py
luadata/serializer/__test__.py
luadata/serializer/serialize.py
luadata/serializer/unserialize.py
luadata-1.0.5.dist-info/LICENSE
luadata-1.0.5.dist-info/METADATA
luadata-1.0.5.dist-info/WHEEL
luadata-1.0.5.dist-info/top_level.txt
luadata-1.0.5.dist-info/RECORD
