Metadata-Version: 2.1
Name: luadata
Version: 1.0.5
Summary: Serialize and unserialize Python list & dictionary between Lua table.
Home-page: https://github.com/leafvmaple/luadata
Author: Zohar Lee
Author-email: leafvmaple@gmail.com
License: BSD License
Keywords: lua,data,luadata,table
Platform: any
Classifier: License :: OSI Approved :: BSD License
Classifier: Development Status :: 4 - Beta
Classifier: Operating System :: OS Independent
Classifier: Programming Language :: Python :: 3
